setup.py
calc_distribution/Binomialdistribution.py
calc_distribution/Gaussiandistribution.py
calc_distribution/Generaldistribution.py
calc_distribution/__init__.py
calc_distribution.egg-info/PKG-INFO
calc_distribution.egg-info/SOURCES.txt
calc_distribution.egg-info/dependency_links.txt
calc_distribution.egg-info/not-zip-safe
calc_distribution.egg-info/top_level.txt